[
  {
    "_id": "5c53f8a1cd80ff4d9aa95842",
    "age": 37,
    "name": {
      "first": "Jamie",
      "last": "Guy"
    },
    "company": "ORGANICA",
    "email": "shannon.lawson@plutorque.com",
    "phone": "+1 (906) 565-3705"
  },
  {
    "_id": "5c53f8a1a22032efec016eaf",
    "age": 40,
    "name": {
      "first": "Wyatt",
      "last": "Avila"
    },
    "company": "QIMONK",
    "email": "wyatt.avila@qimonk.me",
    "phone": "+1 (933) 494-2204"
  },
  {
    "_id": "5c53f8a149b51affdd99a05a",
    "age": 27,
    "name": {
      "first": "Valencia",
      "last": "Vance"
    },
    "company": "GALLAXIA",
    "email": "valencia.vance@gallaxia.tv",
    "phone": "+1 (966) 472-3372"
  },
  {
    "_id": "5c53f8a1be390d947062be3a",
    "age": 37,
    "name": {
      "first": "Jo",
      "last": "Cleveland"
    },
    "company": "BUZZWORKS",
    "email": "jo.cleveland@buzzworks.info",
    "phone": "+1 (964) 441-2764"
  },
  {
    "_id": "5c53f8a1f420994ffef0fe00",
    "age": 20,
    "name": {
      "first": "Ginger",
      "last": "Scott"
    },
    "company": "ESCHOIR",
    "email": "ginger.scott@eschoir.org",
    "phone": "+1 (831) 474-2816"
  },
  {
    "_id": "5c53f8a1e4cfa8d753d4cba3",
    "age": 33,
    "name": {
      "first": "Karyn",
      "last": "Barber"
    },
    "company": "QUILM",
    "email": "karyn.barber@quilm.us",
    "phone": "+1 (997) 508-2703"
  },
  {
    "_id": "5c53f8a12d4fac64ba29ce68",
    "age": 32,
    "name": {
      "first": "Peterson",
      "last": "Hendrix"
    },
    "company": "ZOLAREX",
    "email": "peterson.hendrix@zolarex.io",
    "phone": "+1 (926) 450-2470"
  },
  {
    "_id": "5c53f8a16d257be894d2f65d",
    "age": 22,
    "name": {
      "first": "Cathy",
      "last": "Welch"
    },
    "company": "NAMEBOX",
    "email": "cathy.welch@namebox.biz",
    "phone": "+1 (969) 408-3179"
  },
  {
    "_id": "5c53f8a1e3357521e2d23a9d",
    "age": 24,
    "name": {
      "first": "Estella",
      "last": "Odonnell"
    },
    "company": "SPORTAN",
    "email": "estella.odonnell@sportan.biz",
    "phone": "+1 (902) 472-3714"
  },
  {
    "_id": "5c53f8a1b0f304e6d041ae10",
    "age": 36,
    "name": {
      "first": "Cantu",
      "last": "Good"
    },
    "company": "ZAGGLE",
    "email": "cantu.good@zaggle.name",
    "phone": "+1 (938) 584-3073"
  },
  {
    "_id": "5c53f8a1859f9b8d42b7da8a",
    "age": 27,
    "name": {
      "first": "Sears",
      "last": "Conley"
    },
    "company": "FREAKIN",
    "email": "sears.conley@freakin.co.uk",
    "phone": "+1 (822) 560-3172"
  },
  {
    "_id": "5c53f8a16ef4cda198cbd933",
    "age": 33,
    "name": {
      "first": "Pearson",
      "last": "Harvey"
    },
    "company": "RECRISYS",
    "email": "pearson.harvey@recrisys.net",
    "phone": "+1 (805) 429-3641"
  },
  {
    "_id": "5c53f8a16ee959022a2a01da",
    "age": 31,
    "name": {
      "first": "Gaines",
      "last": "Short"
    },
    "company": "OULU",
    "email": "gaines.short@oulu.com",
    "phone": "+1 (951) 520-2029"
  },
  {
    "_id": "5c53f8a1f8ace100159e8770",
    "age": 40,
    "name": {
      "first": "Puckett",
      "last": "Trujillo"
    },
    "company": "TASMANIA",
    "email": "puckett.trujillo@tasmania.me",
    "phone": "+1 (914) 494-3680"
  },
  {
    "_id": "5c53f8a14fa14482643969b0",
    "age": 34,
    "name": {
      "first": "Terra",
      "last": "Buckner"
    },
    "company": "SULTRAX",
    "email": "terra.buckner@sultrax.tv",
    "phone": "+1 (885) 532-2306"
  },
  {
    "_id": "5c53f8a16cdca74ec6a748f3",
    "age": 24,
    "name": {
      "first": "Harriett",
      "last": "Alvarez"
    },
    "company": "COMTEXT",
    "email": "harriett.alvarez@comtext.info",
    "phone": "+1 (892) 477-3300"
  },
  {
    "_id": "5c53f8a13c58d249e7e7689b",
    "age": 39,
    "name": {
      "first": "Mason",
      "last": "Collins"
    },
    "company": "ZBOO",
    "email": "mason.collins@zboo.org",
    "phone": "+1 (938) 464-3970"
  },
  {
    "_id": "5c53f8a1d33732cb89a740cf",
    "age": 40,
    "name": {
      "first": "Maldonado",
      "last": "Bentley"
    },
    "company": "STELAECOR",
    "email": "maldonado.bentley@stelaecor.us",
    "phone": "+1 (865) 405-3964"
  },
  {
    "_id": "5c53f8a191072d5eb5b1de24",
    "age": 40,
    "name": {
      "first": "Macdonald",
      "last": "Compton"
    },
    "company": "QUORDATE",
    "email": "macdonald.compton@quordate.io",
    "phone": "+1 (940) 520-2395"
  },
  {
    "_id": "5c53f8a197f36dcb3c608595",
    "age": 35,
    "name": {
      "first": "Stella",
      "last": "Kelly"
    },
    "company": "ESSENSIA",
    "email": "stella.kelly@essensia.biz",
    "phone": "+1 (806) 429-2555"
  },
  {
    "_id": "5c53f8a156879910efef56b3",
    "age": 31,
    "name": {
      "first": "Osborne",
      "last": "Dean"
    },
    "company": "HIVEDOM",
    "email": "osborne.dean@hivedom.biz",
    "phone": "+1 (976) 475-3677"
  },
  {
    "_id": "5c53f8a1ceda9ad173e207fd",
    "age": 37,
    "name": {
      "first": "Myra",
      "last": "Hays"
    },
    "company": "PIGZART",
    "email": "myra.hays@pigzart.name",
    "phone": "+1 (828) 577-3466"
  },
  {
    "_id": "5c53f8a197a8fc2616be16a3",
    "age": 22,
    "name": {
      "first": "Minnie",
      "last": "Kidd"
    },
    "company": "ISODRIVE",
    "email": "minnie.kidd@isodrive.co.uk",
    "phone": "+1 (829) 598-3626"
  },
  {
    "_id": "5c53f8a101763c33c24faf6b",
    "age": 39,
    "name": {
      "first": "Le",
      "last": "Douglas"
    },
    "company": "SKYPLEX",
    "email": "le.douglas@skyplex.net",
    "phone": "+1 (986) 438-2353"
  },
  {
    "_id": "5c53f8a1cc830e393ef53ec3",
    "age": 40,
    "name": {
      "first": "Hancock",
      "last": "Mack"
    },
    "company": "COREPAN",
    "email": "hancock.mack@corepan.com",
    "phone": "+1 (899) 584-2098"
  },
  {
    "_id": "5c53f8a18f91805465fe4f09",
    "age": 32,
    "name": {
      "first": "Rosetta",
      "last": "Green"
    },
    "company": "EXOTERIC",
    "email": "rosetta.green@exoteric.me",
    "phone": "+1 (888) 554-2287"
  },
  {
    "_id": "5c53f8a1f670aa81cdde5a2a",
    "age": 28,
    "name": {
      "first": "Kathy",
      "last": "Ingram"
    },
    "company": "LOTRON",
    "email": "kathy.ingram@lotron.tv",
    "phone": "+1 (845) 494-3571"
  },
  {
    "_id": "5c53f8a1cc528dde7ad06d4f",
    "age": 20,
    "name": {
      "first": "Berger",
      "last": "Velez"
    },
    "company": "COMVENE",
    "email": "berger.velez@comvene.info",
    "phone": "+1 (884) 402-3704"
  },
  {
    "_id": "5c53f8a15d823534b2ed6c1b",
    "age": 27,
    "name": {
      "first": "Erin",
      "last": "Delaney"
    },
    "company": "DAYCORE",
    "email": "erin.delaney@daycore.org",
    "phone": "+1 (891) 495-3597"
  },
  {
    "_id": "5c53f8a13d71fa7116fba27f",
    "age": 24,
    "name": {
      "first": "Meredith",
      "last": "Hahn"
    },
    "company": "EVENTAGE",
    "email": "meredith.hahn@eventage.us",
    "phone": "+1 (988) 455-3417"
  },
  {
    "_id": "5c53f8a194076794a26c8d7f",
    "age": 27,
    "name": {
      "first": "Figueroa",
      "last": "York"
    },
    "company": "ECLIPSENT",
    "email": "figueroa.york@eclipsent.io",
    "phone": "+1 (907) 423-3735"
  },
  {
    "_id": "5c53f8a19197f108ea9722e2",
    "age": 20,
    "name": {
      "first": "Mabel",
      "last": "Macias"
    },
    "company": "TERRAGO",
    "email": "mabel.macias@terrago.biz",
    "phone": "+1 (888) 595-2323"
  },
  {
    "_id": "5c53f8a1f4f8d86e12ea402e",
    "age": 20,
    "name": {
      "first": "Kelsey",
      "last": "Higgins"
    },
    "company": "GENMOM",
    "email": "kelsey.higgins@genmom.biz",
    "phone": "+1 (887) 575-2109"
  },
  {
    "_id": "5c53f8a1b5c236c3a10e7bd3",
    "age": 28,
    "name": {
      "first": "Beulah",
      "last": "Boyer"
    },
    "company": "VIDTO",
    "email": "beulah.boyer@vidto.name",
    "phone": "+1 (887) 460-2021"
  },
  {
    "_id": "5c53f8a130c6ef9dc3cdbbf3",
    "age": 31,
    "name": {
      "first": "Leon",
      "last": "Hobbs"
    },
    "company": "MEDMEX",
    "email": "leon.hobbs@medmex.co.uk",
    "phone": "+1 (934) 453-3533"
  },
  {
    "_id": "5c53f8a1bb4921a85aff97de",
    "age": 20,
    "name": {
      "first": "Crosby",
      "last": "Lindsey"
    },
    "company": "ZILLA",
    "email": "crosby.lindsey@zilla.net",
    "phone": "+1 (950) 472-3497"
  },
  {
    "_id": "5c53f8a1109fe14c527edec4",
    "age": 35,
    "name": {
      "first": "Tabitha",
      "last": "Cabrera"
    },
    "company": "IMPERIUM",
    "email": "tabitha.cabrera@imperium.com",
    "phone": "+1 (936) 571-2656"
  },
  {
    "_id": "5c53f8a1fd83a860099605b2",
    "age": 34,
    "name": {
      "first": "Serena",
      "last": "Dejesus"
    },
    "company": "SIGNIDYNE",
    "email": "serena.dejesus@signidyne.me",
    "phone": "+1 (829) 513-3057"
  },
  {
    "_id": "5c53f8a177469f9290099495",
    "age": 22,
    "name": {
      "first": "Sadie",
      "last": "Aguilar"
    },
    "company": "RUGSTARS",
    "email": "sadie.aguilar@rugstars.tv",
    "phone": "+1 (936) 411-3609"
  },
  {
    "_id": "5c53f8a1121966acc7940d98",
    "age": 29,
    "name": {
      "first": "Morin",
      "last": "Young"
    },
    "company": "ACLIMA",
    "email": "morin.young@aclima.info",
    "phone": "+1 (830) 460-2378"
  },
  {
    "_id": "5c53f8a12531e8a9b84fa356",
    "age": 26,
    "name": {
      "first": "Chandra",
      "last": "Cohen"
    },
    "company": "PREMIANT",
    "email": "chandra.cohen@premiant.org",
    "phone": "+1 (898) 407-2744"
  },
  {
    "_id": "5c53f8a1a85deb086f386f27",
    "age": 35,
    "name": {
      "first": "Franklin",
      "last": "Glover"
    },
    "company": "BEDDER",
    "email": "franklin.glover@bedder.us",
    "phone": "+1 (867) 425-2537"
  },
  {
    "_id": "5c53f8a13590aa36042b1c01",
    "age": 37,
    "name": {
      "first": "Queen",
      "last": "Moses"
    },
    "company": "GENMEX",
    "email": "queen.moses@genmex.io",
    "phone": "+1 (815) 581-3150"
  },
  {
    "_id": "5c53f8a118f3c3939a71adf1",
    "age": 31,
    "name": {
      "first": "Angela",
      "last": "Harrington"
    },
    "company": "ENQUILITY",
    "email": "angela.harrington@enquility.biz",
    "phone": "+1 (876) 497-3593"
  },
  {
    "_id": "5c53f8a13dd3cd9cae4338f1",
    "age": 40,
    "name": {
      "first": "Perez",
      "last": "Salazar"
    },
    "company": "NUTRALAB",
    "email": "perez.salazar@nutralab.biz",
    "phone": "+1 (846) 458-2204"
  },
  {
    "_id": "5c53f8a1da27542106116b92",
    "age": 36,
    "name": {
      "first": "Rosalyn",
      "last": "Best"
    },
    "company": "GAZAK",
    "email": "rosalyn.best@gazak.name",
    "phone": "+1 (950) 516-2230"
  },
  {
    "_id": "5c53f8a1121c5882f0d39a03",
    "age": 33,
    "name": {
      "first": "Torres",
      "last": "Rollins"
    },
    "company": "COWTOWN",
    "email": "torres.rollins@cowtown.co.uk",
    "phone": "+1 (859) 474-2113"
  },
  {
    "_id": "5c53f8a1c432ec014f43c598",
    "age": 31,
    "name": {
      "first": "Hardy",
      "last": "Nichols"
    },
    "company": "PLASMOX",
    "email": "hardy.nichols@plasmox.net",
    "phone": "+1 (953) 472-3331"
  },
  {
    "_id": "5c53f8a12a2ac462549ec247",
    "age": 20,
    "name": {
      "first": "Fitzgerald",
      "last": "Bowman"
    },
    "company": "JUNIPOOR",
    "email": "fitzgerald.bowman@junipoor.com",
    "phone": "+1 (925) 425-3411"
  },
  {
    "_id": "5c53f8a1012c97317a17ee88",
    "age": 27,
    "name": {
      "first": "Myers",
      "last": "Morse"
    },
    "company": "KEGULAR",
    "email": "myers.morse@kegular.me",
    "phone": "+1 (946) 536-2396"
  },
  {
    "_id": "5c53f8a10b585f8c854f3442",
    "age": 22,
    "name": {
      "first": "Aida",
      "last": "Elliott"
    },
    "company": "ANDRYX",
    "email": "aida.elliott@andryx.tv",
    "phone": "+1 (840) 414-3077"
  },
  {
    "_id": "5c53f8a106a83c07d4aa7727",
    "age": 22,
    "name": {
      "first": "Janet",
      "last": "Banks"
    },
    "company": "CYCLONICA",
    "email": "janet.banks@cyclonica.info",
    "phone": "+1 (955) 453-3410"
  },
  {
    "_id": "5c53f8a18182108774ddb2a6",
    "age": 30,
    "name": {
      "first": "Esther",
      "last": "Logan"
    },
    "company": "KLUGGER",
    "email": "esther.logan@klugger.org",
    "phone": "+1 (825) 541-3067"
  },
  {
    "_id": "5c53f8a1ff3cb6ce0f63bfac",
    "age": 39,
    "name": {
      "first": "Welch",
      "last": "Morales"
    },
    "company": "EZENT",
    "email": "welch.morales@ezent.us",
    "phone": "+1 (851) 440-2025"
  },
  {
    "_id": "5c53f8a128a734790e10173d",
    "age": 25,
    "name": {
      "first": "Boyd",
      "last": "Jacobson"
    },
    "company": "REMOLD",
    "email": "boyd.jacobson@remold.io",
    "phone": "+1 (906) 440-3145"
  },
  {
    "_id": "5c53f8a11094c8211b46441b",
    "age": 23,
    "name": {
      "first": "Moreno",
      "last": "Frederick"
    },
    "company": "PETICULAR",
    "email": "moreno.frederick@peticular.biz",
    "phone": "+1 (886) 528-2638"
  },
  {
    "_id": "5c53f8a135bdc7868388aa8b",
    "age": 26,
    "name": {
      "first": "Martha",
      "last": "Wheeler"
    },
    "company": "ULTRIMAX",
    "email": "martha.wheeler@ultrimax.biz",
    "phone": "+1 (896) 527-3621"
  },
  {
    "_id": "5c53f8a1742220b1d68aa23d",
    "age": 31,
    "name": {
      "first": "Amalia",
      "last": "Lopez"
    },
    "company": "QUADEEBO",
    "email": "amalia.lopez@quadeebo.name",
    "phone": "+1 (922) 571-2555"
  },
  {
    "_id": "5c53f8a1e8113adac7c3484e",
    "age": 33,
    "name": {
      "first": "Acosta",
      "last": "Frank"
    },
    "company": "ANOCHA",
    "email": "acosta.frank@anocha.co.uk",
    "phone": "+1 (805) 573-2761"
  },
  {
    "_id": "5c53f8a1a8fbce81b44bb03c",
    "age": 21,
    "name": {
      "first": "Bailey",
      "last": "Tyson"
    },
    "company": "OZEAN",
    "email": "bailey.tyson@ozean.net",
    "phone": "+1 (844) 498-3503"
  },
  {
    "_id": "5c53f8a18b6a39127f4fd29f",
    "age": 27,
    "name": {
      "first": "Cooley",
      "last": "Steele"
    },
    "company": "PARCOE",
    "email": "cooley.steele@parcoe.com",
    "phone": "+1 (920) 440-3122"
  },
  {
    "_id": "5c53f8a156b860d03dfca745",
    "age": 36,
    "name": {
      "first": "Bentley",
      "last": "Cochran"
    },
    "company": "GENMY",
    "email": "bentley.cochran@genmy.me",
    "phone": "+1 (828) 499-2819"
  },
  {
    "_id": "5c53f8a1490ac6d100c649dd",
    "age": 32,
    "name": {
      "first": "Deleon",
      "last": "Richards"
    },
    "company": "EXOSPEED",
    "email": "deleon.richards@exospeed.tv",
    "phone": "+1 (884) 416-2093"
  },
  {
    "_id": "5c53f8a12bd94348f276f8b0",
    "age": 27,
    "name": {
      "first": "Gwen",
      "last": "Shepard"
    },
    "company": "CINESANCT",
    "email": "gwen.shepard@cinesanct.info",
    "phone": "+1 (896) 481-2899"
  },
  {
    "_id": "5c53f8a18aea0548da1f3b81",
    "age": 27,
    "name": {
      "first": "Acevedo",
      "last": "Holman"
    },
    "company": "VELITY",
    "email": "acevedo.holman@velity.org",
    "phone": "+1 (922) 454-2453"
  },
  {
    "_id": "5c53f8a1e8d78c78425c95db",
    "age": 24,
    "name": {
      "first": "Claudia",
      "last": "Dixon"
    },
    "company": "BITENDREX",
    "email": "claudia.dixon@bitendrex.us",
    "phone": "+1 (935) 599-3507"
  },
  {
    "_id": "5c53f8a1b867912d4a6cc91f",
    "age": 38,
    "name": {
      "first": "Beryl",
      "last": "Obrien"
    },
    "company": "FURNAFIX",
    "email": "beryl.obrien@furnafix.io",
    "phone": "+1 (931) 537-2369"
  },
  {
    "_id": "5c53f8a1ad0785bb9bf5de5f",
    "age": 37,
    "name": {
      "first": "Shanna",
      "last": "Fisher"
    },
    "company": "XINWARE",
    "email": "shanna.fisher@xinware.biz",
    "phone": "+1 (889) 522-3275"
  },
  {
    "_id": "5c53f8a18547ce42b62550b7",
    "age": 29,
    "name": {
      "first": "Charity",
      "last": "Mccormick"
    },
    "company": "ECRATIC",
    "email": "charity.mccormick@ecratic.biz",
    "phone": "+1 (865) 426-3215"
  },
  {
    "_id": "5c53f8a1a122f8eea48536db",
    "age": 35,
    "name": {
      "first": "Gill",
      "last": "Rodgers"
    },
    "company": "TECHADE",
    "email": "gill.rodgers@techade.name",
    "phone": "+1 (947) 499-3208"
  }
]